spexPy/automl.py
spexPy/classifiers.py
spexPy/preprocessing.py
spexPy/regressers.py
spexpy-0.0.1.dist-info/LICENSE
spexpy-0.0.1.dist-info/METADATA
spexpy-0.0.1.dist-info/WHEEL
spexpy-0.0.1.dist-info/top_level.txt
spexpy-0.0.1.dist-info/RECORD
