Metadata-Version: 2.1
Name: spexpy
Version: 0.0.1
Summary: Machine learning tuning
Author-email: Zefang Shen <zefang.zef.shen@gmail.com>
Maintainer-email: Zefang Shen <zefang.zef.shen@gmail.com>
License: BSD 3-Clause License
Project-URL: Homepage, https://www.github.com
Project-URL: Documentation, https://www.github.com
Project-URL: Repository, https://www.github.com
Keywords: specifications
Requires-Python: >=3.8
License-File: LICENSE
Requires-Dist: numpy
Requires-Dist: pandas
Requires-Dist: scipy
Requires-Dist: optuna
Requires-Dist: tqdm
